Trail/__init__.py
Trail/abhinav.py
Abhinav-0.0.4.dist-info/LICENSE.txt
Abhinav-0.0.4.dist-info/METADATA
Abhinav-0.0.4.dist-info/WHEEL
Abhinav-0.0.4.dist-info/top_level.txt
Abhinav-0.0.4.dist-info/RECORD
