Metadata-Version: 2.1
Name: Abhinav
Version: 0.0.4
Summary: This package is made by me, means Abhinav Mishra
Home-page: UNKNOWN
Author: Abhinav Mishra
Author-email: abhinavkrishu007@gmail.com
License: UNKNOWN
Keywords: arithmetic,math,mathematics,pyautogui,pyttsx3,best,python,abhicoder,abhinav mishra,abhinav
Platform: UNKNOWN
Classifier: Development Status :: 1 - Planning
Classifier: Intended Audience :: Developers
Classifier: Programming Language :: Python :: 3
Classifier: Operating System :: Unix
Classifier: Operating System :: MacOS :: MacOS X
Classifier: Operating System :: Microsoft :: Windows
License-File: LICENSE.txt
